MANIFEST.in
requirements.txt
setup.py
dataset_model/__init__.py
dataset_model/models.py
dataset_model.egg-info/PKG-INFO
dataset_model.egg-info/SOURCES.txt
dataset_model.egg-info/dependency_links.txt
dataset_model.egg-info/requires.txt
dataset_model.egg-info/top_level.txt
tests/__init__.py
tests/sample_data.py
tests/test_models.py