Metadata-Version: 1.1
Name: dataset-model
Version: 0.1.2
Summary: Easy model object to work with the dataset framework
Home-page: http://github.com/fmartingr/dataset-model
Author: Felipe Martin
Author-email: fmartingr@me.com
License: GPLv2
Keywords: sql sqlalchemy utility dataset
Platform: UNKNOWN
Classifier: Development Status :: 5 - Production/Stable
Classifier: Intended Audience :: Developers
Classifier: Operating System :: OS Independent
Classifier: Programming Language :: Python
